<bindings xmlns="http://www.mozilla.org/xbl"
    xmlns:xbl="http://www.mozilla.org/xbl"
    xmlns:xul="http://www.mozilla.org/keymaster/gatekeeper/there.is.only.xul">

  <binding id="buttonmenu" display="xul:menu" 
           extends="chrome://global/content/bindings/toolbarbutton.xml#toolbarbutton">
    <content>
      <children includes="observes|template|menupopup|tooltip"/>
      <xul:image class="toolbarbutton-icon" xbl:inherits="validate,src=image,toolbarmode,buttonstyle"/>
      <xul:label class="toolbarbutton-text" crop="right" flex="1"
                 xbl:inherits="value=label,accesskey,crop,dragover-top,toolbarmode,buttonstyle"/>
    </content>
  </binding>

  <!-- borrowed from Hit-a-Hint by Pekka P. Sillanpaa (c) -->
  <binding id="keyinputbox">
    <resources>
       <stylesheet src="chrome://fireinput/skin/fireinput.css"/>
    </resources>
    <content>
      <xul:textbox xbl:inherits="size" 
                   readonly="true" 
                   class="keyinputbox" 
                   onkeydown="parentNode.onKeyDown(event);"
                   onkeyup="parentNode.stopEvent(event);return false;"
                   onkeypress="parentNode.stopEvent(event);return false;"
                   onfocus="style.background='#faa';"
                   onblur="style.background='#fff';"
                   />
    </content>
    <implementation>
      <!-- Stores the keyCode and modifiers in a single value -->
      <property name="combinedValue"
                onset="return this.setCombinedValue(val);"
                onget="return this.getCombinedValue();"/>
      <property name="allowModifiers"
                onset="return this.setAttribute('allowmodifiers',val);"
                onget="return this.getAttribute('allowmodifiers');"/>
                <!-- onset="return this.updateAttr('modifiers',val);" -->
      <property name="modifiers"
                onget="return this.getAttribute('modifiers');"/>
                <!-- onset="return this.updateAttr('keycode',val);" -->
      <property name="keyCode"
                onget="return this.getAttribute('keycode');"/>


      <constructor>
        if (this.getAttribute('keycode') != '')
          this.updateDisplay();
      </constructor>

      <method name="updateAttr">
        <parameter name="attr"/>
        <parameter name="value"/>
        <body>
          <![CDATA[
            if (attr == 'modifiers' && this.getAttribute('allowmodifiers') == 'false')
              return false;
            this.setAttribute(attr, value);
            this.updateDisplay();
            return true;
          ]]>
        </body>
      </method>

      <method name="updateDisplay">
        <body>
          document.getAnonymousNodes(this)[0].value = this.keyString();
        </body>
      </method>

      <!-- Returns a displayable representation of the keyCode and modifier values -->
      <method name="keyString">
        <body>
          <![CDATA[
            var str = '';
            var parts;
            var modifiers = this.getAttribute('modifiers');
            var keyCode = this.getAttribute('keycode');
            if (keyCode == '') return '未设';
            str += (modifiers & Event.CONTROL_MASK)?'Ctrl+':'';
            str += (modifiers & Event.ALT_MASK)?'Alt+':'';
            str += (modifiers & Event.SHIFT_MASK)?'Shift+':'';
            str += (modifiers & Event.META_MASK)?'Meta+':''; 
            if(keyCodeMapper!=null)
                return str + keyCodeMapper[keyCode];
            // If no name is set, just use the keyCode
            return str + keyCode;   
          ]]>
        </body>
      </method>

      <method name="onKeyDown">
        <parameter name="event"/>
        <body>
          if (event.keyCode == Event.prototype.DOM_VK_META ||
              event.keyCode == Event.prototype.DOM_VK_SHIFT ||
              event.keyCode == Event.prototype.DOM_VK_CONTROL ||
              event.keyCode == Event.prototype.DOM_VK_ALT)
              return;
          this.setKey(event);
          this.stopEvent(event);
        </body>
      </method>

      <method name="stopEvent">
        <parameter name="event"/>
        <body>
          event.preventDefault();
          event.stopPropagation();
        </body>
      </method>



      <method name="setKey">
        <parameter name="event"/>
        <body>
          if(event.keyCode=="8"){
            this.updateAttr('keycode',"");
            this.updateAttr('modifiers',0);
          }else{
            this.updateAttr('keycode',event.keyCode);
            this.updateAttr('modifiers',this.getModifiers(event));
          }
          this.updateDisplay();
        </body>
      </method>


      <method name="getModifiers">
        <parameter name="event"/>
        <body>
          return event.altKey * Event.ALT_MASK |
                 event.ctrlKey * Event.CONTROL_MASK |
                 event.shiftKey * Event.SHIFT_MASK |
                 event.metaKey * Event.META_MASK;
        </body>
      </method>
      <!-- Returns a string that can be used in the 'modifiers' attribute of the
           XUL <key> element -->
      <method name="getModifierString">
        <body>
          <![CDATA[
            var arr = new Array();
            var modifiers = this.getAttribute('modifiers');
            if (modifiers & Event.CONTROL_MASK) arr.push('accel');
            if (modifiers & Event.SHIFT_MASK) arr.push('shift');
            if (modifiers & Event.ALT_MASK) arr.push('alt');
            if (modifiers & Event.META_MASK) arr.push('meta');
            return arr.join(',');
          ]]>
        </body>
      </method>
      <method name="setCombinedValue">
        <parameter name="value"/>
        <body>
          <![CDATA[
            if(value=="0"){
                this.updateAttr('modifiers', 0);
                this.updateAttr('keycode', "");
            }else{
                this.updateAttr('modifiers', value & 0xF);
                this.updateAttr('keycode', value >> 4);
            }   
          ]]>
        </body>
      </method>

      <method name="getCombinedValue">
        <body>
          <![CDATA[
            return this.keyCode << 4 | this.modifiers;
          ]]>
        </body>
      </method>
    </implementation>
  </binding>
</bindings>

